<?xml version="1.0" encoding="utf-8"?><elementcharlist><elementchar>%u5343</elementchar><elementchar>%u5C11</elementchar><elementchar>%u4E22</elementchar><elementchar>%u58EC</elementchar><elementchar>%u7CFB</elementchar><elementchar>%u5347</elementchar><elementchar>%u79B9</elementchar><elementchar>%u4E4F</elementchar><elementchar>%u5E01</elementchar><elementchar>%u592D</elementchar><elementchar>%u5B85</elementchar><elementchar>%u66F5</elementchar><elementchar>%u4E03</elementchar><elementchar>%u722A</elementchar></elementcharlist>













