<?xml version="1.0" encoding="utf-8"?><elementcharlist><elementchar>%u6795</elementchar><elementchar>%u8BA5</elementchar><elementchar>%u58F3</elementchar><elementchar>%u6050</elementchar><elementchar>%u4E3D</elementchar><elementchar>%u5198</elementchar><elementchar>%u803D</elementchar><elementchar>%u822A</elementchar><elementchar>%u7B51</elementchar><elementchar>%u8239</elementchar><elementchar>%u6297</elementchar><elementchar>%u808C</elementchar><elementchar>%u6C88</elementchar><elementchar>%u6C89</elementchar><elementchar>%u5751</elementchar><elementchar>%u51E0</elementchar><elementchar>%u51E1</elementchar><elementchar>%u51ED</elementchar><elementchar>%u51EF</elementchar><elementchar>%u51F3</elementchar><elementchar>%u4EA2</elementchar><elementchar>%u4EAE</elementchar><elementchar>%u864E</elementchar><elementchar>%u6CBF</elementchar><elementchar>%u5DE9</elementchar><elementchar>%u5FAE</elementchar><elementchar>%u5FBD</elementchar><elementchar>%u9965</elementchar><elementchar>%u8EB2</elementchar><elementchar>%u7FD8</elementchar><elementchar>%u5E06</elementchar><elementchar>%u79C3</elementchar><elementchar>%u7095</elementchar><elementchar>%u4F69</elementchar><elementchar>%u6735</elementchar><elementchar>%u673A</elementchar><elementchar>%u8D62</elementchar></elementcharlist>