<?xml version="1.0" encoding="utf-8"?><elementcharlist><elementchar>%u52F9</elementchar><elementchar>%u52FA</elementchar><elementchar>%u5305</elementchar><elementchar>%u53E5</elementchar><elementchar>%u66F7</elementchar><elementchar>%u82DF</elementchar><elementchar>%u5300</elementchar><elementchar>%u52FE</elementchar><elementchar>%u5308</elementchar><elementchar>%u530B</elementchar><elementchar>%u65EC</elementchar><elementchar>%u4E10</elementchar><elementchar>%u530A</elementchar></elementcharlist>













