<?xml version="1.0" encoding="utf-8"?><elementcharlist><elementchar>%u5315</elementchar><elementchar>%u8001</elementchar><elementchar>%u6B64</elementchar><elementchar>%u80FD</elementchar><elementchar>%u5B83</elementchar><elementchar>%u5C3C</elementchar><elementchar>%u6BD4</elementchar><elementchar>%u5317</elementchar><elementchar>%u6B7B</elementchar><elementchar>%u4ED1</elementchar><elementchar>%u65E8</elementchar><elementchar>%u7591</elementchar><elementchar>%u9F99</elementchar><elementchar>%u5319</elementchar><elementchar>%u988D</elementchar></elementcharlist>















