<?xml version="1.0" encoding="utf-8"?><elementlist><def> porter ::  husband, man</def><pro>fu1 :: fu1</pro><usage><usageel><gb>%B4%F3%B7%F2</gb><uni>%u5927%u592B</uni></usageel><usageel><gb>%B7%F2%B8%BE</gb><uni>%u592B%u5987</uni></usageel><usageel><gb>%B7%F2%C6%DE</gb><uni>%u592B%u59BB</uni></usageel><usageel><gb>%B7%F2%C8%CB</gb><uni>%u592B%u4EBA</uni></usageel><usageel><gb>%B9%A4%B7%F2</gb><uni>%u5DE5%u592B</uni></usageel><usageel><gb>%B9%A5%B7%F2</gb><uni>%u653B%u592B</uni></usageel><usageel><gb>%D5%C9%B7%F2</gb><uni>%u4E08%u592B</uni></usageel><usageel><gb>%B9%A6%B7%F2</gb><uni>%u529F%u592B</uni></usageel></usage><elementid>%u592B</elementid><elementid>%u4E8C</elementid><elementid>%u4EBA</elementid></elementlist>






