<?xml version="1.0" encoding="utf-8"?><elementlist><def> to hurry or rush, to run quickly, to elope ::  go to, towards</def><pro>ben1 :: ben4</pro><usage><usageel><gb>%B1%BC</gb><uni>%u5954</uni></usageel><usageel><gb>%B1%BC%B3%DB</gb><uni>%u5954%u9A70</uni></usageel><usageel><gb>%B1%BC%C5%DC</gb><uni>%u5954%u8DD1</uni></usageel><usageel><gb>%B1%BC%CC%DA</gb><uni>%u5954%u817E</uni></usageel><usageel><gb>%B1%BC</gb><uni>%u5954</uni></usageel><usageel><gb>%B6%AB%B1%BC%CE%F7%D7%DF</gb><uni>%u4E1C%u5954%u897F%u8D70</uni></usageel><usageel><gb>%B8%F7%B1%BC%C7%B0%B3%CC</gb><uni>%u5404%u5954%u524D%u7A0B</uni></usageel><usageel><gb>%B1%BC%B2%A8</gb><uni>%u5954%u6CE2</uni></usageel></usage><elementid>%u5954</elementid><elementid>%u5927</elementid><elementid>%u5349</elementid></elementlist>






