<?xml version="1.0" encoding="utf-8"?><elementlist><def> , room, CL:%u500B|%u4E2A[ge4], </def><pro>shi4</pro><usage><usageel><gb>%B0%EC%B9%AB%CA%D2</gb><uni>%u529E%u516C%u5BA4</uni></usageel><usageel><gb>%94%9C%CA%D2</gb><uni>%u654E%u5BA4</uni></usageel><usageel><gb>%94%9C%B3%78%CA%D2</gb><uni>%u654E%u784F%u5BA4</uni></usageel><usageel><gb>%BE%D3%CA%D2</gb><uni>%u5C45%u5BA4</uni></usageel><usageel><gb>%CA%D2</gb><uni>%u5BA4</uni></usageel><usageel><gb>%CE%D4%CA%D2</gb><uni>%u5367%u5BA4</uni></usageel><usageel><gb>%D2%BD%CE%F1%CA%D2</gb><uni>%u533B%u52A1%u5BA4</uni></usageel><usageel><gb>%D4%A1%CA%D2</gb><uni>%u6D74%u5BA4</uni></usageel><usageel><gb>%D4%C4%C0%C0%CA%D2</gb><uni>%u9605%u89C8%u5BA4</uni></usageel><usageel><gb>%BD%CC%CA%D2</gb><uni>%u6559%u5BA4</uni></usageel></usage><elementid>%u5BA4</elementid><elementid>%u81F3</elementid><elementid>i_5B83_1</elementid></elementlist>


