<?xml version="1.0" encoding="utf-8"?><elementlist><def> to break (e.g. stick or bone), a loss ::  to turn sth over, to turn upside-down, to tip sth out (of a container) ::  to break, to fracture, to snap, to suffer loss, to bend, to twist, to turn, to change direction, convinced, to convert into (currency), discount, rebate, tenth (in price), classifier for theatrical scenes, to fold, accounts book ::  to fold (a document), to turn, to bend</def><pro>she2 :: zhe1 :: zhe2 :: zhe2</pro><usage><usageel><gb>%B4%EC%D5%DB</gb><uni>%u632B%u6298</uni></usageel><usageel><gb>%C7%FA%D5%DB</gb><uni>%u66F2%u6298</uni></usageel><usageel><gb>%D5%DB%CC%DA</gb><uni>%u6298%u817E</uni></usageel><usageel><gb>%D5%DB</gb><uni>%u6298</uni></usageel><usageel><gb>%D5%DB%BA%CF</gb><uni>%u6298%u5408</uni></usageel><usageel><gb>%D5%DB%C4%A5</gb><uni>%u6298%u78E8</uni></usageel><usageel><gb>%D6%DC%D5%DB</gb><uni>%u5468%u6298</uni></usageel><usageel><gb>%D7%AA%D5%DB</gb><uni>%u8F6C%u6298</uni></usageel><usageel><gb>%B4%F2%D5%DB</gb><uni>%u6253%u6298</uni></usageel></usage><elementid>%u6298</elementid><elementid>i_6302_1</elementid><elementid>%u65A4</elementid></elementlist>






