<?xml version="1.0" encoding="utf-8"?><elementlist><def> , to explore, to search out, to scout, to visit, to stretch forward, </def><pro>tan4</pro><usage><usageel><gb>%BF%B1%CC%BD</gb><uni>%u52D8%u63A2</uni></usageel><usageel><gb>%CC%BD</gb><uni>%u63A2</uni></usageel><usageel><gb>%CC%BD%B2%E2</gb><uni>%u63A2%u6D4B</uni></usageel><usageel><gb>%CC%BD%C7%D7</gb><uni>%u63A2%u4EB2</uni></usageel><usageel><gb>%CC%BD%CB%F7</gb><uni>%u63A2%u7D22</uni></usageel><usageel><gb>%CC%BD%CC%D6</gb><uni>%u63A2%u8BA8</uni></usageel><usageel><gb>%CC%BD%CD%B7%CC%BD%C4%D4</gb><uni>%u63A2%u5934%u63A2%u8111</uni></usageel><usageel><gb>%CC%BD%CD%B7%CC%BD%C4%D4</gb><uni>%u63A2%u5934%u63A2%u8111</uni></usageel><usageel><gb>%CC%BD%CD%FB</gb><uni>%u63A2%u671B</uni></usageel><usageel><gb>%D5%EC%CC%BD</gb><uni>%u4FA6%u63A2</uni></usageel></usage><elementid>%u63A2</elementid><elementid>%u7A74</elementid><elementid>%u6728</elementid><elementid>i_6302_1</elementid></elementlist>


