<?xml version="1.0" encoding="utf-8"?><elementlist><def> , next in sequence, second, the second (day, time etc), secondary, vice-, sub-, infra-, inferior quality, substandard, order, sequence, hypo- (chemistry), classifier for enumerated events: time, </def><pro>ci4</pro><usage><usageel><gb>%B2%E3%B4%CE</gb><uni>%u5C42%u6B21</uni></usageel><usageel><gb>%B4%CE</gb><uni>%u6B21</uni></usageel><usageel><gb>%B4%CE</gb><uni>%u6B21</uni></usageel><usageel><gb>%B4%CE%C6%B7</gb><uni>%u6B21%u54C1</uni></usageel><usageel><gb>%B4%CE%CA%FD</gb><uni>%u6B21%u6570</uni></usageel><usageel><gb>%B4%CE%D0%F2</gb><uni>%u6B21%u5E8F</uni></usageel><usageel><gb>%B4%CE%D2%AA</gb><uni>%u6B21%u8981</uni></usageel><usageel><gb>%B5%B5%B4%CE</gb><uni>%u6863%u6B21</uni></usageel><usageel><gb>%C3%FB%B4%CE</gb><uni>%u540D%u6B21</uni></usageel><usageel><gb>%C6%E4%B4%CE</gb><uni>%u5176%u6B21</uni></usageel><usageel><gb>%C8%FD%B7%AC%CE%E5%B4%CE</gb><uni>%u4E09%u756A%u4E94%u6B21</uni></usageel><usageel><gb>%D2%C0%B4%CE</gb><uni>%u4F9D%u6B21</uni></usageel><usageel><gb>%C2%C5%B4%CE</gb><uni>%u5C61%u6B21</uni></usageel></usage><elementid>%u6B21</elementid><elementid>%u6B20</elementid><elementid>i_6B21_1</elementid></elementlist>


