<?xml version="1.0" encoding="utf-8"?><elementlist><def> , disaster, calamity, </def><pro>zai1</pro><usage><usageel><gb>%BA%B5%D4%D6</gb><uni>%u65F1%u707E</uni></usageel><usageel><gb>%BB%F0%D4%D6</gb><uni>%u706B%u707E</uni></usageel><usageel><gb>%BE%C8%D4%D6</gb><uni>%u6551%u707E</uni></usageel><usageel><gb>%CB%AE%D4%D6</gb><uni>%u6C34%u707E</uni></usageel><usageel><gb>%D4%D6</gb><uni>%u707E</uni></usageel><usageel><gb>%D4%D6%BA%A6</gb><uni>%u707E%u5BB3</uni></usageel><usageel><gb>%D4%D6%BB%C4</gb><uni>%u707E%u8352</uni></usageel><usageel><gb>%D4%D6%C4%D1</gb><uni>%u707E%u96BE</uni></usageel></usage><elementid>%u707E</elementid><elementid>i_5B83_1</elementid><elementid>%u706B</elementid></elementlist>


