<?xml version="1.0" encoding="utf-8"?><elementlist><def> , precious thing, treasure, </def><pro>zhen1</pro><usage><usageel><gb>%D5%E4%B9%F3</gb><uni>%u73CD%u8D35</uni></usageel><usageel><gb>%D5%E4%CF%A7</gb><uni>%u73CD%u60DC</uni></usageel><usageel><gb>%D5%E4%D6%E9</gb><uni>%u73CD%u73E0</uni></usageel><usageel><gb>%D5%E4%CF%A1</gb><uni>%u73CD%u7A00</uni></usageel></usage><elementid>%u73CD</elementid><elementid>%u738B</elementid><elementid>%u4EBA</elementid><elementid>i_5F69_1</elementid></elementlist>



