<?xml version="1.0" encoding="utf-8"?><elementlist><def> , to follow, from, it is for...to, reason, cause, because of, due to, to, to leave it (to sb), by (introduces passive verb), </def><pro>you2</pro><usage><usageel><gb>%B2%BB%D3%C9%B5%C3</gb><uni>%u4E0D%u7531%u5F97</uni></usageel><usageel><gb>%C0%ED%D3%C9</gb><uni>%u7406%u7531</uni></usageel><usageel><gb>%D3%C9</gb><uni>%u7531</uni></usageel><usageel><gb>%D3%C9%B4%CB%BF%C9%BC%FB</gb><uni>%u7531%u6B64%u53EF%u89C1</uni></usageel><usageel><gb>%D3%C9%D3%DA</gb><uni>%u7531%u4E8E</uni></usageel><usageel><gb>%D7%D4%D3%C9</gb><uni>%u81EA%u7531</uni></usageel><usageel><gb>%D7%D4%D3%C9%CA%D0%B3%A1</gb><uni>%u81EA%u7531%u5E02%u573A</uni></usageel></usage><elementid>%u7531</elementid><elementid>%u7530</elementid><elementid>%u4E28</elementid></elementlist>


