<?xml version="1.0" encoding="utf-8"?><elementlist><def> fussy, talkative ::  subordinate in a gang of bandits ::  gauze, to collect; to gather, to catch, to sift; to sieve, surname Luo</def><pro>luo1 :: luo2 :: luo2</pro><usage><usageel><gb>%C2%DE%CB%F4</gb><uni>%u7F57%u5506</uni></usageel><usageel><gb>%C2%DE%C1%D0</gb><uni>%u7F57%u5217</uni></usageel><usageel><gb>%C2%DE%E0%C2</gb><uni>%u7F57%u55E6</uni></usageel></usage><elementid>%u7F57</elementid><elementid>i_7F72_1</elementid><elementid>%u5915</elementid></elementlist>







