<?xml version="1.0" encoding="utf-8"?><elementcharlist><elementchar>%u8096</elementchar><elementchar>%u6D88</elementchar><elementchar>%u7A0D</elementchar><elementchar>%u6084</elementchar><elementchar>%u4FCF</elementchar><elementchar>%u54E8</elementchar><elementchar>%u5BB5</elementchar><elementchar>%u524A</elementchar><elementchar>%u9500</elementchar><elementchar>%u5CED</elementchar><elementchar>%u68A2</elementchar><elementchar>%u5C51</elementchar><elementchar>%u634E</elementchar></elementcharlist>













