<?xml version="1.0" encoding="utf-8"?><elementlist><def> , dialect, language, spoken words, speech, talk, words, conversation, what sb said, CL:%u7A2E|%u79CD[zhong3],%u5E2D[xi2],%u53E5[ju4],%u53E3[kou3],%u756A[fan1], </def><pro>hua4</pro><usage><usageel><gb>%B2%E8%BB%B0%BB%E1</gb><uni>%u8336%u8BDD%u4F1A</uni></usageel><usageel><gb>%A1%AD%B5%C4%BB%B0</gb><uni>%u2026%u7684%u8BDD</uni></usageel><usageel><gb>%B5%E7%BB%B0</gb><uni>%u7535%u8BDD</uni></usageel><usageel><gb>%B6%D4%BB%B0</gb><uni>%u5BF9%u8BDD</uni></usageel><usageel><gb>%B7%CF%BB%B0</gb><uni>%u5E9F%u8BDD</uni></usageel><usageel><gb>%B9%AB%D3%C3%B5%E7%BB%B0</gb><uni>%u516C%u7528%u7535%u8BDD</uni></usageel><usageel><gb>%BB%B0</gb><uni>%u8BDD</uni></usageel><usageel><gb>%BB%B0%BE%E7</gb><uni>%u8BDD%u5267</uni></usageel><usageel><gb>%BB%B0%CC%E2</gb><uni>%u8BDD%u9898</uni></usageel><usageel><gb>%BB%E1%BB%B0</gb><uni>%u4F1A%u8BDD</uni></usageel><usageel><gb>%BD%B2%BB%B0</gb><uni>%u8BB2%u8BDD</uni></usageel><usageel><gb>%BF%D5%BB%B0</gb><uni>%u7A7A%u8BDD</uni></usageel><usageel><gb>%C6%D5%CD%A8%BB%B0</gb><uni>%u666E%u901A%u8BDD</uni></usageel><usageel><gb>%C9%F1%BB%B0</gb><uni>%u795E%u8BDD</uni></usageel><usageel><gb>%CA%B5%BB%B0</gb><uni>%u5B9E%u8BDD</uni></usageel><usageel><gb>%CB%D7%BB%B0</gb><uni>%u4FD7%u8BDD</uni></usageel><usageel><gb>%CC%B8%BB%B0</gb><uni>%u8C08%u8BDD</uni></usageel><usageel><gb>%CC%B8%BB%B0</gb><uni>%u8C08%u8BDD</uni></usageel><usageel><gb>%CF%D0%BB%B0</gb><uni>%u95F2%u8BDD</uni></usageel><usageel><gb>%D0%A6%BB%B0</gb><uni>%u7B11%u8BDD</uni></usageel><usageel><gb>%B2%BB%CF%F1%BB%B0</gb><uni>%u4E0D%u50CF%u8BDD</uni></usageel><usageel><gb>%B4%F2%B5%E7%BB%B0</gb><uni>%u6253%u7535%u8BDD</uni></usageel><usageel><gb>%BB%B0%CD%B2</gb><uni>%u8BDD%u7B52</uni></usageel><usageel><gb>%CB%B5%BB%B0</gb><uni>%u8BF4%u8BDD</uni></usageel><usageel><gb>%CD%AF%BB%B0</gb><uni>%u7AE5%u8BDD</uni></usageel></usage><elementid>%u8BDD</elementid><elementid>%u820C</elementid><elementid>%u8BA0</elementid></elementlist>




