<?xml version="1.0" encoding="utf-8"?><elementlist><def> , to catch up, to overtake, to hurry, to rush, to drive away, </def><pro>gan3</pro><usage><usageel><gb>%B8%CF</gb><uni>%u8D76</uni></usageel><usageel><gb>%B8%CF%BD%F4</gb><uni>%u8D76%u7D27</uni></usageel><usageel><gb>%B8%CF%BF%EC</gb><uni>%u8D76%u5FEB</uni></usageel><usageel><gb>%B8%CF%C3%A6</gb><uni>%u8D76%u5FD9</uni></usageel><usageel><gb>%B8%CF%C9%CF</gb><uni>%u8D76%u4E0A</uni></usageel><usageel><gb>%D7%B7%B8%CF</gb><uni>%u8FFD%u8D76</uni></usageel></usage><elementid>%u8D76</elementid><elementid>%u5E72</elementid><elementid>%u8D70</elementid></elementlist>


