<?xml version="1.0" encoding="utf-8"?><elementlist><def> , to move, to transport, to use, to apply, fortune, luck, fate, </def><pro>yun4</pro><usage><usageel><gb>%B0%E1%D4%CB</gb><uni>%u642C%u8FD0</uni></usageel><usageel><gb>%BA%BD%D4%CB</gb><uni>%u822A%u8FD0</uni></usageel><usageel><gb>%C3%FC%D4%CB</gb><uni>%u547D%u8FD0</uni></usageel><usageel><gb>%D0%D2%D4%CB</gb><uni>%u5E78%u8FD0</uni></usageel><usageel><gb>%D4%CB</gb><uni>%u8FD0</uni></usageel><usageel><gb>%D4%CB%B6%AF</gb><uni>%u8FD0%u52A8</uni></usageel><usageel><gb>%D4%CB%B6%AF%BB%E1</gb><uni>%u8FD0%u52A8%u4F1A</uni></usageel><usageel><gb>%D4%CB%B6%AF%D4%B1</gb><uni>%u8FD0%u52A8%u5458</uni></usageel><usageel><gb>%D4%CB%C6%F8</gb><uni>%u8FD0%u6C14</uni></usageel><usageel><gb>%D4%CB%CA%E4</gb><uni>%u8FD0%u8F93</uni></usageel><usageel><gb>%D4%CB%CB%CD</gb><uni>%u8FD0%u9001</uni></usageel><usageel><gb>%D4%CB%CB%E3</gb><uni>%u8FD0%u7B97</uni></usageel><usageel><gb>%D4%CB%D0%D0</gb><uni>%u8FD0%u884C</uni></usageel><usageel><gb>%D4%CB%D3%C3</gb><uni>%u8FD0%u7528</uni></usageel><usageel><gb>%D4%CB%D7%AA</gb><uni>%u8FD0%u8F6C</uni></usageel><usageel><gb>%CD%D0%D4%CB</gb><uni>%u6258%u8FD0</uni></usageel></usage><elementid>%u8FD0</elementid><elementid>%u4E91</elementid><elementid>i_8FDC_1</elementid></elementlist>


