<?xml version="1.0" encoding="utf-8"?><elementlist><def> , to wake up, to awaken, to be awake, </def><pro>xing3</pro><usage><usageel><gb>%BE%F5%D0%D1</gb><uni>%u89C9%u9192</uni></usageel><usageel><gb>%9C%5B%D0%D1</gb><uni>%u6DF8%u9192</uni></usageel><usageel><gb>%CB%D5%D0%D1</gb><uni>%u82CF%u9192</uni></usageel><usageel><gb>%CC%E1%D0%D1</gb><uni>%u63D0%u9192</uni></usageel><usageel><gb>%D0%D1</gb><uni>%u9192</uni></usageel><usageel><gb>%C7%E5%D0%D1</gb><uni>%u6E05%u9192</uni></usageel></usage><elementid>%u9192</elementid><elementid>%u9149</elementid><elementid>%u661F</elementid></elementlist>


